virgo/__init__.py
virgo/py.typed
virgo/actions/__init__.py
virgo/actions/generate.py
virgo/actions/protocols.py
virgo/actions/py.typed
virgo/agent/__init__.py
virgo/agent/chains.py
virgo/agent/factories.py
virgo/agent/graph.py
virgo/agent/llms.py
virgo/agent/prompts.py
virgo/agent/py.typed
virgo/agent/schemas.py
virgo/agent/tools.py
virgo/cli/__init__.py
virgo/cli/commands.py
virgo/cli/container.py
virgo/cli/py.typed
virgo_agent-1.1.0.dist-info/METADATA
virgo_agent-1.1.0.dist-info/WHEEL
virgo_agent-1.1.0.dist-info/entry_points.txt
virgo_agent-1.1.0.dist-info/licenses/LICENCE
virgo_agent-1.1.0.dist-info/RECORD
