Metadata-Version: 2.4
Name: virgo-agent
Version: 1.1.0
Summary: Assistant to generate, review and improve articles.
License-File: LICENCE
Requires-Python: >=3.14
Requires-Dist: dependency-injector>=4.48.3
Requires-Dist: langchain-openai>=1.1.1
Requires-Dist: langchain-tavily>=0.2.13
Requires-Dist: langchain>=1.1.3
Requires-Dist: langgraph>=1.0.4
Requires-Dist: pydantic-settings>=2.12.0
Requires-Dist: pydantic>=2.12.5
Requires-Dist: rich>=14.2.0
Requires-Dist: typer>=0.20.0
